databankpy/__init__.py
databankpy/main.py
databankpy-0.0.1.dist-info/LICENSE.txt
databankpy-0.0.1.dist-info/METADATA
databankpy-0.0.1.dist-info/WHEEL
databankpy-0.0.1.dist-info/top_level.txt
databankpy-0.0.1.dist-info/RECORD
